{"products" :[
  { "id": 1, "name": "Product A", "votes": 324 },
  { "id": 2, "name": "Product B", "votes": 235 },
  { "id": 3, "name": "Product C", "votes": 688 },
  { "id": 4, "name": "Product D", "votes": 312 },
  { "id": 5, "name": "Product E", "votes": 319 },
  { "id": 6, "name": "Product F", "votes": 411 },
  { "id": 7, "name": "Product G", "votes": 99 },
  { "id": 8, "name": "Product H", "votes": 387 },
  { "id": 9, "name": "Product I", "votes": 742 },
  { "id": 10, "name": "Product J", "votes": 999 },
  { "id": 11, "name": "Product K", "votes": 123 },
  { "id": 12, "name": "Product L", "votes": 544 }
]}
